{
  "format_version": "1.20.30",
  "minecraft:feature_rules": {
    "description": {
      "identifier": "cc:birch_tree_rule",
      "places_feature": "cc:birch_tree_sequence"
    },
    "conditions": {
      "placement_pass": "surface_pass",
      "minecraft:biome_filter": {
        "all_of": [
          {
            "test": "has_biome_tag",
            "operator": "==",
            "value": "forest"
          },
          {
            "test": "has_biome_tag",
            "operator": "==",
            "value": "birch"
          }
        ],
        "none_of": [
          {
            "test": "has_biome_tag",
            "operator": "==",
            "value": "roofed"
          },
          {
            "test": "has_biome_tag",
            "operator": "==",
            "value": "taiga"
          }
        ]
      }
    },
    "distribution": {
      "iterations": "math.random(20, 30)",
      "x": {
        "distribution": "uniform",
        "extent": [
          -8,
          8
        ]
      },
      "y": "query.heightmap(v.originx, v.originz)",
      "z": {
        "distribution": "uniform",
        "extent": [
          -8,
          8
        ]
      }
    }
  }
}