{
  "format_version": "1.16.100",
  "minecraft:fog_settings": {
    "description": {
      "identifier": "pa:wewkwjkwkwwiwwbe"
    },
    "distance": {
      "air": {
        "fog_start": 0.2976995940460081,
        "fog_end": 0.5087956698240865,
        "fog_color": "#ffacfb",
        "render_distance_type": "render"
      },
      "water": {
        "fog_start": 0.0,
        "fog_end": 60.0,
        "fog_color": "#44AFF5",
        "render_distance_type": "fixed",
        "transition_fog": {
          "min_percent": 0.25,
          "mid_percent": 0.6,
          "mid_seconds": 5.0,
          "max_seconds": 30.0,
          "init_fog": {
            "fog_start": 0.0,
            "fog_end": 0.01,
            "fog_color": "#44AFF5",
            "render_distance_type": "fixed"
          }
        }
      },
      "weather": {
        "fog_start": 0.23,
        "fog_end": 0.7,
        "fog_color": "#303030",
        "render_distance_type": "render"
      },
      "lava": {
        "fog_start": 0.0,
        "fog_end": 71.04194857916103,
        "fog_color": "#991A00",
        "render_distance_type": "fixed"
      },
      "lava_resistance": {
        "fog_start": 2.0,
        "fog_end": 102.84167794316643,
        "fog_color": "#991A00",
        "render_distance_type": "fixed"
      }
    }
  }
}