{
	"format_version": "1.21.60",
	"minecraft:block": {
		"description": {
			"identifier": "korbon:sulfur_ore",
			"menu_category": {
				"category": "nature",
				"group": "minecraft:itemGroup.name.ore",
				"states": {
				}
			}
		},
		"components": {
			"minecraft:material_instances": {
				"*": {
					"texture": "sulfur_ore",
					"render_method": "opaque",
					"face_dimming": true
				}
			},
			"minecraft:loot": "loot_tables/blocks/sulfur.json",
			"minecraft:destructible_by_explosion": {
				"explosion_resistance": 1
			},
			"minecraft:geometry": "minecraft:geometry.full_block",
			"minecraft:custom_components": [
				"korbon:spawnxp"
			],
			"minecraft:destructible_by_mining": {
				"seconds_to_destroy": 4
			},
			"tag:minecraft:is_pickaxe_item_destructible": {}
		}
	}
}